drf_cbor/__init__.py
drf_cbor/parse.py
drf_cbor/render.py
django_rest_cbor-0.0.1.dist-info/LICENSE
django_rest_cbor-0.0.1.dist-info/METADATA
django_rest_cbor-0.0.1.dist-info/WHEEL
django_rest_cbor-0.0.1.dist-info/top_level.txt
django_rest_cbor-0.0.1.dist-info/RECORD
