Metadata-Version: 2.1
Name: django-rest-cbor
Version: 0.0.1
Summary: Django Rest Framework CBOR Renderer & Parser
Home-page: https://github.com/lthibault/django-rest-cbor
Author: lthibault
Author-email: UNKNOWN
License: UNKNOWN
Platform: UNKNOWN
Requires-Dist: django
Requires-Dist: cbor2
Requires-Dist: djangorestframework
